LICENSE
MANIFEST.in
README.rst
setup.cfg
setup.py
test/tests.py
test_data/abc.xml
test_data/po.xml
xmldestroyer/__init__.py
xmldestroyer.egg-info/PKG-INFO
xmldestroyer.egg-info/SOURCES.txt
xmldestroyer.egg-info/dependency_links.txt
xmldestroyer.egg-info/requires.txt
xmldestroyer.egg-info/top_level.txt
xmldestroyer.egg-info/zip-safe