Metadata-Version: 1.1
Name: xmldestroyer
Version: 0.2
Summary: Bottom-up transformation of XML into python generators, XML, JSON or text.
Home-page: http://github.com/danr/xmldestroyer
Author: Dan Rosén
Author-email: dan.rosen@gu.se
License: MIT
Keywords: xml bottom up bottom-up transformation syb scrap your boilerplate scrap-your-boilerplate uniplate geniplate
Platform: UNKNOWN
Classifier: Development Status :: 2 - Pre-Alpha
Classifier: Topic :: Text Processing :: Markup :: XML
Classifier: License :: OSI Approved
Classifier: License :: OSI Approved :: MIT License
Classifier: Intended Audience :: Developers
Classifier: Programming Language :: Python :: 2
Classifier: Programming Language :: Python :: 3
